setup.py
lite_messenger_server.egg-info/PKG-INFO
lite_messenger_server.egg-info/SOURCES.txt
lite_messenger_server.egg-info/dependency_links.txt
lite_messenger_server.egg-info/requires.txt
lite_messenger_server.egg-info/top_level.txt
server/__init__.py
server/server.py
server/common/__init__.py
server/common/decorators.py
server/common/descryptors.py
server/common/errors.py
server/common/metaclasses.py
server/common/settings.py
server/common/utils.py
server/logs/__init__.py
server/logs/client_log_config.py
server/logs/server_log_config.py
server/server/__init__.py
server/server/add_user.py
server/server/config_window.py
server/server/core.py
server/server/database.py
server/server/main_window.py
server/server/remove_user.py
server/server/stat_window.py
server/tests/__init__.py