Metadata-Version: 1.0
Name: lite-messenger-server
Version: 0.0.1
Summary: lite_messenger_server
Home-page: UNKNOWN
Author: Dmitry Grodzinsky
Author-email: dmitry.ml@mail.ru
License: UNKNOWN
Platform: UNKNOWN
